maestro/__init__.py
maestro_app-0.0.1.dist-info/DESCRIPTION.rst
maestro_app-0.0.1.dist-info/METADATA
maestro_app-0.0.1.dist-info/RECORD
maestro_app-0.0.1.dist-info/WHEEL
maestro_app-0.0.1.dist-info/entry_points.txt
maestro_app-0.0.1.dist-info/metadata.json
maestro_app-0.0.1.dist-info/top_level.txt
maestro_app-0.0.1.dist-info/zip-safe
