Metadata-Version: 2.0
Name: maestro-app
Version: 0.0.1
Summary: Music practice on steroids.
Home-page: https://github.com/urosjarc/maestro
Author: Uroš Jarc
Author-email: jar.fmf@gmail.com
License: MIT license
Keywords: maestro
Platform: UNKNOWN
Classifier: Development Status :: 2 - Pre-Alpha
Classifier: Intended Audience :: Developers
Classifier: License :: OSI Approved :: MIT License
Classifier: Natural Language :: English
Classifier: Programming Language :: Python :: 2
Classifier: Programming Language :: Python :: 2.6
Classifier: Programming Language :: Python :: 2.7
Classifier: Programming Language :: Python :: 3
Classifier: Programming Language :: Python :: 3.3
Classifier: Programming Language :: Python :: 3.4
Classifier: Programming Language :: Python :: 3.5
Requires-Dist: pyqt5
